<?xml version="1.0" encoding="utf-8" ?><dwsync><file name="drop.css" server="1977.com.ar//clientes/veterinarios2/" local="3443557520" remote="318763443889279572" Dst="-1" /><file name="pregunta1.css" server="1977.com.ar//clientes/veterinarios2/" local="3457975908" remote="318763443889279572" Dst="-1" /><file name="bootstrap.css" server="1977.com.ar//clientes/veterinarios2/" local="3496153574" remote="318763443889279572" Dst="-1" /><file name="pregunta2.css" server="1977.com.ar//clientes/veterinarios2/" local="3458055780" remote="318763443889279572" Dst="-1" /><file name="pregunta3.css" server="1977.com.ar//clientes/veterinarios2/" local="3458059666" remote="318763443889279572" Dst="-1" /><file name="style-gato.css" server="1977.com.ar//clientes/veterinarios2/" local="3496198668" remote="318763443889279572" Dst="-1" /><file name="style-perro.css" server="1977.com.ar//clientes/veterinarios2/" local="3496184198" remote="318763443889279572" Dst="-1" /><file name="style.css" server="1977.com.ar//clientes/veterinarios2/" local="3496397372" remote="318763443889279572" Dst="-1" /></dwsync>